seeq/addons/udf_ui/__init__.py
seeq/addons/udf_ui/__main__.py
seeq/addons/udf_ui/_add_on_main.py
seeq/addons/udf_ui/_copy.py
seeq/addons/udf_ui/_version.py
seeq/addons/udf_ui/backend/__init__.py
seeq/addons/udf_ui/backend/_backend.py
seeq/addons/udf_ui/backend/_fetch_udfs.py
seeq/addons/udf_ui/backend/_push_udfs.py
seeq/addons/udf_ui/backend/_udf_classes.py
seeq/addons/udf_ui/backend/_utility_functions.py
seeq/addons/udf_ui/deployment_notebook/UDF_UI_deployment.ipynb
seeq/addons/udf_ui/ui_components/__init__.py
seeq/addons/udf_ui/ui_components/_access_management.py
seeq/addons/udf_ui/ui_components/_app_layout.py
seeq/addons/udf_ui/ui_components/_function_documentation.py
seeq/addons/udf_ui/ui_components/_function_parameters_display.py
seeq/addons/udf_ui/ui_components/_search_display.py
seeq/addons/udf_ui/ui_components/_summary_page.py
seeq/addons/udf_ui/ui_components/templates/AccessManagement.vue
seeq/addons/udf_ui/ui_components/templates/AppLayout.vue
seeq/addons/udf_ui/ui_components/templates/FunctionDocumentation.vue
seeq/addons/udf_ui/ui_components/templates/FunctionParametersDisplay.vue
seeq/addons/udf_ui/ui_components/templates/SearchDisplay.vue
seeq/addons/udf_ui/ui_components/templates/SummaryPage.vue
seeq_udf_ui-0.2.0.dist-info/LICENSE
seeq_udf_ui-0.2.0.dist-info/METADATA
seeq_udf_ui-0.2.0.dist-info/NOTICE
seeq_udf_ui-0.2.0.dist-info/WHEEL
seeq_udf_ui-0.2.0.dist-info/top_level.txt
seeq_udf_ui-0.2.0.dist-info/RECORD
