Metadata-Version: 2.1
Name: seeq-udf-ui
Version: 0.2.0
Summary: A Seeq add-on tool for managing user-defined formula functions.
Home-page: https://github.com/seeq12/udf-ui
Author: Ehsan Shahidi
Author-email: ehsan.shahidi@seeq.com
License: Apache License 2.0
Platform: UNKNOWN
Classifier: Programming Language :: Python :: 3.8
Classifier: License :: OSI Approved :: Apache Software License
Classifier: Operating System :: OS Independent
Requires-Python: >=3.7
License-File: LICENSE
License-File: NOTICE
Requires-Dist: ipywidgets >=7.6.3
Requires-Dist: ipyvuetify >=1.8.0
Requires-Dist: rx >=3.2.0
Requires-Dist: traitlets >=5.1.0
Requires-Dist: IPython >=7.25.0
Requires-Dist: typeguard >=2.13.0
Requires-Dist: mixpanel >=4.9.0
Requires-Dist: Markdown >=3.3.4
Requires-Dist: unmarkd ==0.1.7
